{
 "custom_fields": [
  {
   "_assign": null,
   "_comments": null,
   "_liked_by": null,
   "_user_tags": null,
   "allow_in_quick_entry": 0,
   "allow_on_submit": 0,
   "bold": 0,
   "collapsible": 0,
   "collapsible_depends_on": null,
   "columns": 0,
   "creation": "2025-02-09 20:49:56.398215",
   "default": null,
   "depends_on": null,
   "description": null,
   "docstatus": 0,
   "dt": "Dispatch Form",
   "fetch_from": null,
   "fetch_if_empty": 0,
   "fieldname": "custom_arrival_time_at_dropoff_point",
   "fieldtype": "Datetime",
   "hidden": 1,
   "hide_border": 0,
   "hide_days": 0,
   "hide_seconds": 0,
   "idx": 9,
   "ignore_user_permissions": 0,
   "ignore_xss_filter": 0,
   "in_global_search": 0,
   "in_list_view": 0,
   "in_preview": 0,
   "in_standard_filter": 0,
   "insert_after": "custom_sample_temps",
   "is_system_generated": 0,
   "is_virtual": 0,
   "label": "Arrival Time At Drop-Off point",
   "length": 0,
   "link_filters": null,
   "mandatory_depends_on": null,
   "modified": "2025-02-09 20:49:56.398215",
   "modified_by": "Administrator",
   "module": null,
   "name": "Dispatch Form-custom_arrival_time_at_dropoff_point",
   "no_copy": 0,
   "non_negative": 0,
   "options": null,
   "owner": "Administrator",
   "permlevel": 0,
   "placeholder": null,
   "precision": "",
   "print_hide": 0,
   "print_hide_if_no_value": 0,
   "print_width": null,
   "read_only": 0,
   "read_only_depends_on": null,
   "report_hide": 0,
   "reqd": 0,
   "search_index": 0,
   "show_dashboard": 0,
   "sort_options": 0,
   "translatable": 0,
   "unique": 0,
   "width": null
  },
  {
   "_assign": null,
   "_comments": null,
   "_liked_by": null,
   "_user_tags": null,
   "allow_in_quick_entry": 0,
   "allow_on_submit": 0,
   "bold": 0,
   "collapsible": 0,
   "collapsible_depends_on": null,
   "columns": 0,
   "creation": "2025-02-09 20:54:28.045022",
   "default": null,
   "depends_on": null,
   "description": null,
   "docstatus": 0,
   "dt": "Dispatch Form",
   "fetch_from": null,
   "fetch_if_empty": 0,
   "fieldname": "custom_column_break_pdozs",
   "fieldtype": "Column Break",
   "hidden": 0,
   "hide_border": 0,
   "hide_days": 0,
   "hide_seconds": 0,
   "idx": 6,
   "ignore_user_permissions": 0,
   "ignore_xss_filter": 0,
   "in_global_search": 0,
   "in_list_view": 0,
   "in_preview": 0,
   "in_standard_filter": 0,
   "insert_after": "custom_date",
   "is_system_generated": 0,
   "is_virtual": 0,
   "label": "",
   "length": 0,
   "link_filters": null,
   "mandatory_depends_on": null,
   "modified": "2025-02-09 20:54:28.045022",
   "modified_by": "Administrator",
   "module": null,
   "name": "Dispatch Form-custom_column_break_pdozs",
   "no_copy": 0,
   "non_negative": 0,
   "options": null,
   "owner": "Administrator",
   "permlevel": 0,
   "placeholder": null,
   "precision": "",
   "print_hide": 0,
   "print_hide_if_no_value": 0,
   "print_width": null,
   "read_only": 0,
   "read_only_depends_on": null,
   "report_hide": 0,
   "reqd": 0,
   "search_index": 0,
   "show_dashboard": 0,
   "sort_options": 0,
   "translatable": 0,
   "unique": 0,
   "width": null
  },
  {
   "_assign": null,
   "_comments": null,
   "_liked_by": null,
   "_user_tags": null,
   "allow_in_quick_entry": 0,
   "allow_on_submit": 0,
   "bold": 0,
   "collapsible": 0,
   "collapsible_depends_on": null,
   "columns": 0,
   "creation": "2025-02-09 21:06:32.686805",
   "default": null,
   "depends_on": null,
   "description": null,
   "docstatus": 0,
   "dt": "Dispatch Form",
   "fetch_from": null,
   "fetch_if_empty": 0,
   "fieldname": "custom_column_break_vppm6",
   "fieldtype": "Column Break",
   "hidden": 0,
   "hide_border": 0,
   "hide_days": 0,
   "hide_seconds": 0,
   "idx": 23,
   "ignore_user_permissions": 0,
   "ignore_xss_filter": 0,
   "in_global_search": 0,
   "in_list_view": 0,
   "in_preview": 0,
   "in_standard_filter": 0,
   "insert_after": "custom_shipment_confirmation_awb_signature",
   "is_system_generated": 0,
   "is_virtual": 0,
   "label": "",
   "length": 0,
   "link_filters": null,
   "mandatory_depends_on": null,
   "modified": "2025-02-09 21:06:32.686805",
   "modified_by": "Administrator",
   "module": null,
   "name": "Dispatch Form-custom_column_break_vppm6",
   "no_copy": 0,
   "non_negative": 0,
   "options": null,
   "owner": "Administrator",
   "permlevel": 0,
   "placeholder": null,
   "precision": "",
   "print_hide": 0,
   "print_hide_if_no_value": 0,
   "print_width": null,
   "read_only": 0,
   "read_only_depends_on": null,
   "report_hide": 0,
   "reqd": 0,
   "search_index": 0,
   "show_dashboard": 0,
   "sort_options": 0,
   "translatable": 0,
   "unique": 0,
   "width": null
  },
  {
   "_assign": null,
   "_comments": null,
   "_liked_by": null,
   "_user_tags": null,
   "allow_in_quick_entry": 0,
   "allow_on_submit": 0,
   "bold": 0,
   "collapsible": 0,
   "collapsible_depends_on": null,
   "columns": 0,
   "creation": "2025-02-09 21:06:31.279300",
   "default": null,
   "depends_on": null,
   "description": null,
   "docstatus": 0,
   "dt": "Dispatch Form",
   "fetch_from": null,
   "fetch_if_empty": 0,
   "fieldname": "custom_column_break_y2q6x",
   "fieldtype": "Column Break",
   "hidden": 0,
   "hide_border": 0,
   "hide_days": 0,
   "hide_seconds": 0,
   "idx": 17,
   "ignore_user_permissions": 0,
   "ignore_xss_filter": 0,
   "in_global_search": 0,
   "in_list_view": 0,
   "in_preview": 0,
   "in_standard_filter": 0,
   "insert_after": "custom_dispatch_time",
   "is_system_generated": 0,
   "is_virtual": 0,
   "label": "",
   "length": 0,
   "link_filters": null,
   "mandatory_depends_on": null,
   "modified": "2025-02-09 21:06:31.279300",
   "modified_by": "Administrator",
   "module": null,
   "name": "Dispatch Form-custom_column_break_y2q6x",
   "no_copy": 0,
   "non_negative": 0,
   "options": null,
   "owner": "Administrator",
   "permlevel": 0,
   "placeholder": null,
   "precision": "",
   "print_hide": 0,
   "print_hide_if_no_value": 0,
   "print_width": null,
   "read_only": 0,
   "read_only_depends_on": null,
   "report_hide": 0,
   "reqd": 0,
   "search_index": 0,
   "show_dashboard": 0,
   "sort_options": 0,
   "translatable": 0,
   "unique": 0,
   "width": null
  },
  {
   "_assign": null,
   "_comments": null,
   "_liked_by": null,
   "_user_tags": null,
   "allow_in_quick_entry": 0,
   "allow_on_submit": 0,
   "bold": 0,
   "collapsible": 0,
   "collapsible_depends_on": null,
   "columns": 0,
   "creation": "2025-02-09 21:06:32.210151",
   "default": null,
   "depends_on": null,
   "description": null,
   "docstatus": 0,
   "dt": "Dispatch Form",
   "fetch_from": null,
   "fetch_if_empty": 0,
   "fieldname": "custom_comments",
   "fieldtype": "Small Text",
   "hidden": 0,
   "hide_border": 0,
   "hide_days": 0,
   "hide_seconds": 0,
   "idx": 21,
   "ignore_user_permissions": 0,
   "ignore_xss_filter": 0,
   "in_global_search": 0,
   "in_list_view": 0,
   "in_preview": 0,
   "in_standard_filter": 0,
   "insert_after": "custom_section_break_63l1f",
   "is_system_generated": 0,
   "is_virtual": 0,
   "label": "Comments",
   "length": 0,
   "link_filters": null,
   "mandatory_depends_on": null,
   "modified": "2025-02-09 21:06:32.210151",
   "modified_by": "Administrator",
   "module": null,
   "name": "Dispatch Form-custom_comments",
   "no_copy": 0,
   "non_negative": 0,
   "options": null,
   "owner": "Administrator",
   "permlevel": 0,
   "placeholder": null,
   "precision": "",
   "print_hide": 0,
   "print_hide_if_no_value": 0,
   "print_width": null,
   "read_only": 0,
   "read_only_depends_on": null,
   "report_hide": 0,
   "reqd": 0,
   "search_index": 0,
   "show_dashboard": 0,
   "sort_options": 0,
   "translatable": 1,
   "unique": 0,
   "width": null
  },
  {
   "_assign": null,
   "_comments": null,
   "_liked_by": null,
   "_user_tags": null,
   "allow_in_quick_entry": 0,
   "allow_on_submit": 0,
   "bold": 0,
   "collapsible": 0,
   "collapsible_depends_on": null,
   "columns": 0,
   "creation": "2025-02-05 10:42:25.639569",
   "default": "Tambuzi Limited",
   "depends_on": null,
   "description": null,
   "docstatus": 0,
   "dt": "Dispatch Form",
   "fetch_from": null,
   "fetch_if_empty": 0,
   "fieldname": "custom_company",
   "fieldtype": "Data",
   "hidden": 0,
   "hide_border": 0,
   "hide_days": 0,
   "hide_seconds": 0,
   "idx": 3,
   "ignore_user_permissions": 0,
   "ignore_xss_filter": 0,
   "in_global_search": 0,
   "in_list_view": 0,
   "in_preview": 0,
   "in_standard_filter": 0,
   "insert_after": "amended_from",
   "is_system_generated": 0,
   "is_virtual": 0,
   "label": "Company",
   "length": 0,
   "link_filters": null,
   "mandatory_depends_on": null,
   "modified": "2025-02-05 10:42:25.639569",
   "modified_by": "Administrator",
   "module": null,
   "name": "Dispatch Form-custom_company",
   "no_copy": 0,
   "non_negative": 0,
   "options": null,
   "owner": "Administrator",
   "permlevel": 0,
   "placeholder": null,
   "precision": "",
   "print_hide": 0,
   "print_hide_if_no_value": 0,
   "print_width": null,
   "read_only": 1,
   "read_only_depends_on": null,
   "report_hide": 0,
   "reqd": 0,
   "search_index": 0,
   "show_dashboard": 0,
   "sort_options": 0,
   "translatable": 0,
   "unique": 0,
   "width": null
  },
  {
   "_assign": null,
   "_comments": null,
   "_liked_by": null,
   "_user_tags": null,
   "allow_in_quick_entry": 0,
   "allow_on_submit": 0,
   "bold": 0,
   "collapsible": 0,
   "collapsible_depends_on": null,
   "columns": 0,
   "creation": "2025-02-09 21:06:32.912692",
   "default": null,
   "depends_on": null,
   "description": null,
   "docstatus": 0,
   "dt": "Dispatch Form",
   "fetch_from": "",
   "fetch_if_empty": 0,
   "fieldname": "custom_compiled_bypacking_supervisor",
   "fieldtype": "Link",
   "hidden": 0,
   "hide_border": 0,
   "hide_days": 0,
   "hide_seconds": 0,
   "idx": 24,
   "ignore_user_permissions": 0,
   "ignore_xss_filter": 0,
   "in_global_search": 0,
   "in_list_view": 0,
   "in_preview": 0,
   "in_standard_filter": 0,
   "insert_after": "custom_column_break_vppm6",
   "is_system_generated": 0,
   "is_virtual": 0,
   "label": "Compiled By(Packing Supervisor)",
   "length": 0,
   "link_filters": null,
   "mandatory_depends_on": null,
   "modified": "2025-02-09 21:06:32.912692",
   "modified_by": "Administrator",
   "module": null,
   "name": "Dispatch Form-custom_compiled_bypacking_supervisor",
   "no_copy": 0,
   "non_negative": 0,
   "options": "User",
   "owner": "Administrator",
   "permlevel": 0,
   "placeholder": null,
   "precision": "",
   "print_hide": 0,
   "print_hide_if_no_value": 0,
   "print_width": null,
   "read_only": 0,
   "read_only_depends_on": null,
   "report_hide": 0,
   "reqd": 0,
   "search_index": 0,
   "show_dashboard": 0,
   "sort_options": 0,
   "translatable": 0,
   "unique": 0,
   "width": null
  },
  {
   "_assign": null,
   "_comments": null,
   "_liked_by": null,
   "_user_tags": null,
   "allow_in_quick_entry": 0,
   "allow_on_submit": 0,
   "bold": 0,
   "collapsible": 0,
   "collapsible_depends_on": null,
   "columns": 0,
   "creation": "2025-02-09 20:54:28.482462",
   "default": null,
   "depends_on": null,
   "description": null,
   "docstatus": 0,
   "dt": "Dispatch Form",
   "fetch_from": null,
   "fetch_if_empty": 0,
   "fieldname": "custom_date",
   "fieldtype": "Date",
   "hidden": 0,
   "hide_border": 0,
   "hide_days": 0,
   "hide_seconds": 0,
   "idx": 5,
   "ignore_user_permissions": 0,
   "ignore_xss_filter": 0,
   "in_global_search": 0,
   "in_list_view": 0,
   "in_preview": 0,
   "in_standard_filter": 0,
   "insert_after": "naming_series",
   "is_system_generated": 0,
   "is_virtual": 0,
   "label": "Date",
   "length": 0,
   "link_filters": null,
   "mandatory_depends_on": null,
   "modified": "2025-02-09 20:54:28.482462",
   "modified_by": "Administrator",
   "module": null,
   "name": "Dispatch Form-custom_date",
   "no_copy": 0,
   "non_negative": 0,
   "options": null,
   "owner": "Administrator",
   "permlevel": 0,
   "placeholder": null,
   "precision": "",
   "print_hide": 0,
   "print_hide_if_no_value": 0,
   "print_width": null,
   "read_only": 0,
   "read_only_depends_on": null,
   "report_hide": 0,
   "reqd": 0,
   "search_index": 0,
   "show_dashboard": 0,
   "sort_options": 0,
   "translatable": 0,
   "unique": 0,
   "width": null
  },
  {
   "_assign": null,
   "_comments": null,
   "_liked_by": null,
   "_user_tags": null,
   "allow_in_quick_entry": 0,
   "allow_on_submit": 0,
   "bold": 0,
   "collapsible": 0,
   "collapsible_depends_on": null,
   "columns": 0,
   "creation": "2025-02-09 21:06:31.047331",
   "default": null,
   "depends_on": null,
   "description": null,
   "docstatus": 0,
   "dt": "Dispatch Form",
   "fetch_from": null,
   "fetch_if_empty": 0,
   "fieldname": "custom_dispatch_time",
   "fieldtype": "Time",
   "hidden": 0,
   "hide_border": 0,
   "hide_days": 0,
   "hide_seconds": 0,
   "idx": 16,
   "ignore_user_permissions": 0,
   "ignore_xss_filter": 0,
   "in_global_search": 0,
   "in_list_view": 0,
   "in_preview": 0,
   "in_standard_filter": 0,
   "insert_after": "custom_total_number_of_boxes_dispatched",
   "is_system_generated": 0,
   "is_virtual": 0,
   "label": "Dispatch Time",
   "length": 0,
   "link_filters": null,
   "mandatory_depends_on": null,
   "modified": "2025-02-09 21:06:31.047331",
   "modified_by": "Administrator",
   "module": null,
   "name": "Dispatch Form-custom_dispatch_time",
   "no_copy": 0,
   "non_negative": 0,
   "options": null,
   "owner": "Administrator",
   "permlevel": 0,
   "placeholder": null,
   "precision": "",
   "print_hide": 0,
   "print_hide_if_no_value": 0,
   "print_width": null,
   "read_only": 0,
   "read_only_depends_on": null,
   "report_hide": 0,
   "reqd": 0,
   "search_index": 0,
   "show_dashboard": 0,
   "sort_options": 0,
   "translatable": 0,
   "unique": 0,
   "width": null
  },
  {
   "_assign": null,
   "_comments": null,
   "_liked_by": null,
   "_user_tags": null,
   "allow_in_quick_entry": 0,
   "allow_on_submit": 0,
   "bold": 0,
   "collapsible": 0,
   "collapsible_depends_on": null,
   "columns": 0,
   "creation": "2025-02-09 20:46:55.877666",
   "default": null,
   "depends_on": null,
   "description": null,
   "docstatus": 0,
   "dt": "Dispatch Form",
   "fetch_from": null,
   "fetch_if_empty": 0,
   "fieldname": "custom_sample_temps",
   "fieldtype": "Float",
   "hidden": 1,
   "hide_border": 0,
   "hide_days": 0,
   "hide_seconds": 0,
   "idx": 8,
   "ignore_user_permissions": 0,
   "ignore_xss_filter": 0,
   "in_global_search": 0,
   "in_list_view": 0,
   "in_preview": 0,
   "in_standard_filter": 0,
   "insert_after": "custom_trip",
   "is_system_generated": 0,
   "is_virtual": 0,
   "label": "Sample Temps",
   "length": 0,
   "link_filters": null,
   "mandatory_depends_on": null,
   "modified": "2025-02-09 20:46:55.877666",
   "modified_by": "Administrator",
   "module": null,
   "name": "Dispatch Form-custom_sample_temps",
   "no_copy": 0,
   "non_negative": 0,
   "options": null,
   "owner": "Administrator",
   "permlevel": 0,
   "placeholder": null,
   "precision": "",
   "print_hide": 0,
   "print_hide_if_no_value": 0,
   "print_width": null,
   "read_only": 0,
   "read_only_depends_on": null,
   "report_hide": 0,
   "reqd": 0,
   "search_index": 0,
   "show_dashboard": 0,
   "sort_options": 0,
   "translatable": 0,
   "unique": 0,
   "width": null
  },
  {
   "_assign": null,
   "_comments": null,
   "_liked_by": null,
   "_user_tags": null,
   "allow_in_quick_entry": 0,
   "allow_on_submit": 0,
   "bold": 0,
   "collapsible": 0,
   "collapsible_depends_on": null,
   "columns": 0,
   "creation": "2025-02-09 21:06:31.961861",
   "default": null,
   "depends_on": null,
   "description": null,
   "docstatus": 0,
   "dt": "Dispatch Form",
   "fetch_from": null,
   "fetch_if_empty": 0,
   "fieldname": "custom_section_break_63l1f",
   "fieldtype": "Section Break",
   "hidden": 0,
   "hide_border": 0,
   "hide_days": 0,
   "hide_seconds": 0,
   "idx": 19,
   "ignore_user_permissions": 0,
   "ignore_xss_filter": 0,
   "in_global_search": 0,
   "in_list_view": 0,
   "in_preview": 0,
   "in_standard_filter": 0,
   "insert_after": "custom_truck_reg_no",
   "is_system_generated": 0,
   "is_virtual": 0,
   "label": "",
   "length": 0,
   "link_filters": null,
   "mandatory_depends_on": null,
   "modified": "2025-02-09 21:06:31.961861",
   "modified_by": "Administrator",
   "module": null,
   "name": "Dispatch Form-custom_section_break_63l1f",
   "no_copy": 0,
   "non_negative": 0,
   "options": null,
   "owner": "Administrator",
   "permlevel": 0,
   "placeholder": null,
   "precision": "",
   "print_hide": 0,
   "print_hide_if_no_value": 0,
   "print_width": null,
   "read_only": 0,
   "read_only_depends_on": null,
   "report_hide": 0,
   "reqd": 0,
   "search_index": 0,
   "show_dashboard": 0,
   "sort_options": 0,
   "translatable": 0,
   "unique": 0,
   "width": null
  },
  {
   "_assign": null,
   "_comments": null,
   "_liked_by": null,
   "_user_tags": null,
   "allow_in_quick_entry": 0,
   "allow_on_submit": 0,
   "bold": 0,
   "collapsible": 0,
   "collapsible_depends_on": null,
   "columns": 0,
   "creation": "2025-02-09 20:53:08.431103",
   "default": null,
   "depends_on": null,
   "description": null,
   "docstatus": 0,
   "dt": "Dispatch Form",
   "fetch_from": null,
   "fetch_if_empty": 0,
   "fieldname": "custom_section_break_fcmtc",
   "fieldtype": "Section Break",
   "hidden": 0,
   "hide_border": 0,
   "hide_days": 0,
   "hide_seconds": 0,
   "idx": 11,
   "ignore_user_permissions": 0,
   "ignore_xss_filter": 0,
   "in_global_search": 0,
   "in_list_view": 0,
   "in_preview": 0,
   "in_standard_filter": 0,
   "insert_after": "custom_week_",
   "is_system_generated": 0,
   "is_virtual": 0,
   "label": "",
   "length": 0,
   "link_filters": null,
   "mandatory_depends_on": null,
   "modified": "2025-02-09 20:53:08.431103",
   "modified_by": "Administrator",
   "module": null,
   "name": "Dispatch Form-custom_section_break_fcmtc",
   "no_copy": 0,
   "non_negative": 0,
   "options": null,
   "owner": "Administrator",
   "permlevel": 0,
   "placeholder": null,
   "precision": "",
   "print_hide": 0,
   "print_hide_if_no_value": 0,
   "print_width": null,
   "read_only": 0,
   "read_only_depends_on": null,
   "report_hide": 0,
   "reqd": 0,
   "search_index": 0,
   "show_dashboard": 0,
   "sort_options": 0,
   "translatable": 0,
   "unique": 0,
   "width": null
  },
  {
   "_assign": null,
   "_comments": null,
   "_liked_by": null,
   "_user_tags": null,
   "allow_in_quick_entry": 0,
   "allow_on_submit": 0,
   "bold": 0,
   "collapsible": 0,
   "collapsible_depends_on": null,
   "columns": 0,
   "creation": "2025-02-09 21:06:30.615093",
   "default": null,
   "depends_on": null,
   "description": null,
   "docstatus": 0,
   "dt": "Dispatch Form",
   "fetch_from": null,
   "fetch_if_empty": 0,
   "fieldname": "custom_section_break_mwy3p",
   "fieldtype": "Section Break",
   "hidden": 0,
   "hide_border": 0,
   "hide_days": 0,
   "hide_seconds": 0,
   "idx": 14,
   "ignore_user_permissions": 0,
   "ignore_xss_filter": 0,
   "in_global_search": 0,
   "in_list_view": 0,
   "in_preview": 0,
   "in_standard_filter": 0,
   "insert_after": "custom_sku_summary",
   "is_system_generated": 0,
   "is_virtual": 0,
   "label": "",
   "length": 0,
   "link_filters": null,
   "mandatory_depends_on": null,
   "modified": "2025-02-09 21:06:30.615093",
   "modified_by": "Administrator",
   "module": null,
   "name": "Dispatch Form-custom_section_break_mwy3p",
   "no_copy": 0,
   "non_negative": 0,
   "options": null,
   "owner": "Administrator",
   "permlevel": 0,
   "placeholder": null,
   "precision": "",
   "print_hide": 0,
   "print_hide_if_no_value": 0,
   "print_width": null,
   "read_only": 0,
   "read_only_depends_on": null,
   "report_hide": 0,
   "reqd": 0,
   "search_index": 0,
   "show_dashboard": 0,
   "sort_options": 0,
   "translatable": 0,
   "unique": 0,
   "width": null
  },
  {
   "_assign": null,
   "_comments": null,
   "_liked_by": null,
   "_user_tags": null,
   "allow_in_quick_entry": 0,
   "allow_on_submit": 0,
   "bold": 0,
   "collapsible": 0,
   "collapsible_depends_on": null,
   "columns": 0,
   "creation": "2025-02-19 11:21:54.280618",
   "default": null,
   "depends_on": null,
   "description": null,
   "docstatus": 0,
   "dt": "Dispatch Form",
   "fetch_from": null,
   "fetch_if_empty": 0,
   "fieldname": "custom_security_supervisor",
   "fieldtype": "Link",
   "hidden": 0,
   "hide_border": 0,
   "hide_days": 0,
   "hide_seconds": 0,
   "idx": 26,
   "ignore_user_permissions": 0,
   "ignore_xss_filter": 0,
   "in_global_search": 0,
   "in_list_view": 0,
   "in_preview": 0,
   "in_standard_filter": 0,
   "insert_after": "custom_signature",
   "is_system_generated": 0,
   "is_virtual": 0,
   "label": "Security Supervisor",
   "length": 0,
   "link_filters": null,
   "mandatory_depends_on": null,
   "modified": "2025-02-19 11:21:54.280618",
   "modified_by": "Administrator",
   "module": null,
   "name": "Dispatch Form-custom_security_supervisor",
   "no_copy": 0,
   "non_negative": 0,
   "options": "Employee",
   "owner": "Administrator",
   "permlevel": 0,
   "placeholder": null,
   "precision": "",
   "print_hide": 0,
   "print_hide_if_no_value": 0,
   "print_width": null,
   "read_only": 0,
   "read_only_depends_on": null,
   "report_hide": 0,
   "reqd": 0,
   "search_index": 0,
   "show_dashboard": 0,
   "sort_options": 0,
   "translatable": 0,
   "unique": 0,
   "width": null
  },
  {
   "_assign": null,
   "_comments": null,
   "_liked_by": null,
   "_user_tags": null,
   "allow_in_quick_entry": 0,
   "allow_on_submit": 0,
   "bold": 0,
   "collapsible": 0,
   "collapsible_depends_on": null,
   "columns": 0,
   "creation": "2025-02-09 21:06:32.452565",
   "default": null,
   "depends_on": null,
   "description": null,
   "docstatus": 0,
   "dt": "Dispatch Form",
   "fetch_from": null,
   "fetch_if_empty": 0,
   "fieldname": "custom_shipment_confirmation_awb_signature",
   "fieldtype": "Signature",
   "hidden": 1,
   "hide_border": 0,
   "hide_days": 0,
   "hide_seconds": 0,
   "idx": 22,
   "ignore_user_permissions": 0,
   "ignore_xss_filter": 0,
   "in_global_search": 0,
   "in_list_view": 0,
   "in_preview": 0,
   "in_standard_filter": 0,
   "insert_after": "custom_comments",
   "is_system_generated": 0,
   "is_virtual": 0,
   "label": "Shipment Confirmation AWB Signature",
   "length": 0,
   "link_filters": null,
   "mandatory_depends_on": null,
   "modified": "2025-02-09 21:06:32.452565",
   "modified_by": "Administrator",
   "module": null,
   "name": "Dispatch Form-custom_shipment_confirmation_awb_signature",
   "no_copy": 0,
   "non_negative": 0,
   "options": null,
   "owner": "Administrator",
   "permlevel": 0,
   "placeholder": null,
   "precision": "",
   "print_hide": 0,
   "print_hide_if_no_value": 0,
   "print_width": null,
   "read_only": 0,
   "read_only_depends_on": null,
   "report_hide": 0,
   "reqd": 0,
   "search_index": 0,
   "show_dashboard": 0,
   "sort_options": 0,
   "translatable": 0,
   "unique": 0,
   "width": null
  },
  {
   "_assign": null,
   "_comments": null,
   "_liked_by": null,
   "_user_tags": null,
   "allow_in_quick_entry": 0,
   "allow_on_submit": 0,
   "bold": 0,
   "collapsible": 0,
   "collapsible_depends_on": null,
   "columns": 0,
   "creation": "2025-02-09 21:13:53.456621",
   "default": null,
   "depends_on": null,
   "description": null,
   "docstatus": 0,
   "dt": "Dispatch Form",
   "fetch_from": null,
   "fetch_if_empty": 0,
   "fieldname": "custom_signature",
   "fieldtype": "Read Only",
   "hidden": 0,
   "hide_border": 0,
   "hide_days": 0,
   "hide_seconds": 0,
   "idx": 25,
   "ignore_user_permissions": 0,
   "ignore_xss_filter": 0,
   "in_global_search": 0,
   "in_list_view": 0,
   "in_preview": 0,
   "in_standard_filter": 0,
   "insert_after": "custom_compiled_bypacking_supervisor",
   "is_system_generated": 0,
   "is_virtual": 0,
   "label": "Signature",
   "length": 0,
   "link_filters": null,
   "mandatory_depends_on": null,
   "modified": "2025-02-09 21:13:53.456621",
   "modified_by": "Administrator",
   "module": null,
   "name": "Dispatch Form-custom_signature",
   "no_copy": 0,
   "non_negative": 0,
   "options": null,
   "owner": "Administrator",
   "permlevel": 0,
   "placeholder": null,
   "precision": "",
   "print_hide": 0,
   "print_hide_if_no_value": 0,
   "print_width": null,
   "read_only": 0,
   "read_only_depends_on": null,
   "report_hide": 0,
   "reqd": 0,
   "search_index": 0,
   "show_dashboard": 0,
   "sort_options": 0,
   "translatable": 0,
   "unique": 0,
   "width": null
  },
  {
   "_assign": null,
   "_comments": null,
   "_liked_by": null,
   "_user_tags": null,
   "allow_in_quick_entry": 0,
   "allow_on_submit": 0,
   "bold": 0,
   "collapsible": 0,
   "collapsible_depends_on": null,
   "columns": 0,
   "creation": "2025-02-19 10:04:38.077697",
   "default": null,
   "depends_on": null,
   "description": null,
   "docstatus": 0,
   "dt": "Dispatch Form",
   "fetch_from": null,
   "fetch_if_empty": 0,
   "fieldname": "custom_sku_summary",
   "fieldtype": "Table",
   "hidden": 0,
   "hide_border": 0,
   "hide_days": 0,
   "hide_seconds": 0,
   "idx": 13,
   "ignore_user_permissions": 0,
   "ignore_xss_filter": 0,
   "in_global_search": 0,
   "in_list_view": 0,
   "in_preview": 0,
   "in_standard_filter": 0,
   "insert_after": "dispatch_form_item",
   "is_system_generated": 0,
   "is_virtual": 0,
   "label": "SKU Summary.",
   "length": 0,
   "link_filters": null,
   "mandatory_depends_on": null,
   "modified": "2025-02-19 10:04:38.077697",
   "modified_by": "Administrator",
   "module": null,
   "name": "Dispatch Form-custom_sku_summary",
   "no_copy": 0,
   "non_negative": 0,
   "options": "SKU Summary",
   "owner": "Administrator",
   "permlevel": 0,
   "placeholder": null,
   "precision": "",
   "print_hide": 0,
   "print_hide_if_no_value": 0,
   "print_width": null,
   "read_only": 0,
   "read_only_depends_on": null,
   "report_hide": 0,
   "reqd": 0,
   "search_index": 0,
   "show_dashboard": 0,
   "sort_options": 0,
   "translatable": 0,
   "unique": 0,
   "width": null
  },
  {
   "_assign": null,
   "_comments": null,
   "_liked_by": null,
   "_user_tags": null,
   "allow_in_quick_entry": 0,
   "allow_on_submit": 0,
   "bold": 0,
   "collapsible": 0,
   "collapsible_depends_on": null,
   "columns": 0,
   "creation": "2025-02-09 21:06:30.832171",
   "default": null,
   "depends_on": null,
   "description": null,
   "docstatus": 0,
   "dt": "Dispatch Form",
   "fetch_from": null,
   "fetch_if_empty": 0,
   "fieldname": "custom_total_number_of_boxes_dispatched",
   "fieldtype": "Int",
   "hidden": 0,
   "hide_border": 0,
   "hide_days": 0,
   "hide_seconds": 0,
   "idx": 15,
   "ignore_user_permissions": 0,
   "ignore_xss_filter": 0,
   "in_global_search": 0,
   "in_list_view": 0,
   "in_preview": 0,
   "in_standard_filter": 0,
   "insert_after": "custom_section_break_mwy3p",
   "is_system_generated": 0,
   "is_virtual": 0,
   "label": "Total Number Of Boxes Dispatched",
   "length": 0,
   "link_filters": null,
   "mandatory_depends_on": null,
   "modified": "2025-02-09 21:06:30.832171",
   "modified_by": "Administrator",
   "module": null,
   "name": "Dispatch Form-custom_total_number_of_boxes_dispatched",
   "no_copy": 0,
   "non_negative": 0,
   "options": null,
   "owner": "Administrator",
   "permlevel": 0,
   "placeholder": null,
   "precision": "",
   "print_hide": 0,
   "print_hide_if_no_value": 0,
   "print_width": null,
   "read_only": 0,
   "read_only_depends_on": null,
   "report_hide": 0,
   "reqd": 0,
   "search_index": 0,
   "show_dashboard": 0,
   "sort_options": 0,
   "translatable": 0,
   "unique": 0,
   "width": null
  },
  {
   "_assign": null,
   "_comments": null,
   "_liked_by": null,
   "_user_tags": null,
   "allow_in_quick_entry": 0,
   "allow_on_submit": 0,
   "bold": 0,
   "collapsible": 0,
   "collapsible_depends_on": null,
   "columns": 0,
   "creation": "2025-02-09 20:54:28.706372",
   "default": "Nairobi",
   "depends_on": null,
   "description": null,
   "docstatus": 0,
   "dt": "Dispatch Form",
   "fetch_from": null,
   "fetch_if_empty": 0,
   "fieldname": "custom_trip",
   "fieldtype": "Data",
   "hidden": 0,
   "hide_border": 0,
   "hide_days": 0,
   "hide_seconds": 0,
   "idx": 7,
   "ignore_user_permissions": 0,
   "ignore_xss_filter": 0,
   "in_global_search": 0,
   "in_list_view": 0,
   "in_preview": 0,
   "in_standard_filter": 0,
   "insert_after": "custom_column_break_pdozs",
   "is_system_generated": 0,
   "is_virtual": 0,
   "label": "Trip",
   "length": 0,
   "link_filters": null,
   "mandatory_depends_on": null,
   "modified": "2025-02-09 20:54:28.706372",
   "modified_by": "Administrator",
   "module": null,
   "name": "Dispatch Form-custom_trip",
   "no_copy": 0,
   "non_negative": 0,
   "options": null,
   "owner": "Administrator",
   "permlevel": 0,
   "placeholder": null,
   "precision": "",
   "print_hide": 0,
   "print_hide_if_no_value": 0,
   "print_width": null,
   "read_only": 0,
   "read_only_depends_on": null,
   "report_hide": 0,
   "reqd": 0,
   "search_index": 0,
   "show_dashboard": 0,
   "sort_options": 0,
   "translatable": 1,
   "unique": 0,
   "width": null
  },
  {
   "_assign": null,
   "_comments": null,
   "_liked_by": null,
   "_user_tags": null,
   "allow_in_quick_entry": 0,
   "allow_on_submit": 0,
   "bold": 0,
   "collapsible": 0,
   "collapsible_depends_on": null,
   "columns": 0,
   "creation": "2025-02-27 11:49:59.078104",
   "default": null,
   "depends_on": null,
   "description": null,
   "docstatus": 0,
   "dt": "Dispatch Form",
   "fetch_from": null,
   "fetch_if_empty": 0,
   "fieldname": "custom_truck_drivers_name",
   "fieldtype": "Link",
   "hidden": 0,
   "hide_border": 0,
   "hide_days": 0,
   "hide_seconds": 0,
   "idx": 18,
   "ignore_user_permissions": 0,
   "ignore_xss_filter": 0,
   "in_global_search": 0,
   "in_list_view": 0,
   "in_preview": 0,
   "in_standard_filter": 0,
   "insert_after": "custom_column_break_y2q6x",
   "is_system_generated": 0,
   "is_virtual": 0,
   "label": "Truck Drivers' Name",
   "length": 0,
   "link_filters": null,
   "mandatory_depends_on": null,
   "modified": "2025-02-27 11:49:59.078104",
   "modified_by": "Administrator",
   "module": null,
   "name": "Dispatch Form-custom_truck_drivers_name",
   "no_copy": 0,
   "non_negative": 0,
   "options": "Employee",
   "owner": "Administrator",
   "permlevel": 0,
   "placeholder": null,
   "precision": "",
   "print_hide": 0,
   "print_hide_if_no_value": 0,
   "print_width": null,
   "read_only": 0,
   "read_only_depends_on": null,
   "report_hide": 0,
   "reqd": 0,
   "search_index": 0,
   "show_dashboard": 0,
   "sort_options": 0,
   "translatable": 0,
   "unique": 0,
   "width": null
  },
  {
   "_assign": null,
   "_comments": null,
   "_liked_by": null,
   "_user_tags": null,
   "allow_in_quick_entry": 0,
   "allow_on_submit": 0,
   "bold": 0,
   "collapsible": 0,
   "collapsible_depends_on": null,
   "columns": 0,
   "creation": "2025-02-27 11:51:13.625168",
   "default": null,
   "depends_on": null,
   "description": null,
   "docstatus": 0,
   "dt": "Dispatch Form",
   "fetch_from": null,
   "fetch_if_empty": 0,
   "fieldname": "custom_truck_reg_no",
   "fieldtype": "Link",
   "hidden": 0,
   "hide_border": 0,
   "hide_days": 0,
   "hide_seconds": 0,
   "idx": 18,
   "ignore_user_permissions": 0,
   "ignore_xss_filter": 0,
   "in_global_search": 0,
   "in_list_view": 0,
   "in_preview": 0,
   "in_standard_filter": 0,
   "insert_after": "custom_truck_drivers_name",
   "is_system_generated": 0,
   "is_virtual": 0,
   "label": "Truck Reg No",
   "length": 0,
   "link_filters": null,
   "mandatory_depends_on": null,
   "modified": "2025-02-27 11:51:13.625168",
   "modified_by": "Administrator",
   "module": null,
   "name": "Dispatch Form-custom_truck_reg_no",
   "no_copy": 0,
   "non_negative": 0,
   "options": "Asset",
   "owner": "Administrator",
   "permlevel": 0,
   "placeholder": null,
   "precision": "",
   "print_hide": 0,
   "print_hide_if_no_value": 0,
   "print_width": null,
   "read_only": 0,
   "read_only_depends_on": null,
   "report_hide": 0,
   "reqd": 0,
   "search_index": 0,
   "show_dashboard": 0,
   "sort_options": 0,
   "translatable": 0,
   "unique": 0,
   "width": null
  },
  {
   "_assign": null,
   "_comments": null,
   "_liked_by": null,
   "_user_tags": null,
   "allow_in_quick_entry": 0,
   "allow_on_submit": 0,
   "bold": 1,
   "collapsible": 0,
   "collapsible_depends_on": null,
   "columns": 0,
   "creation": "2025-02-09 21:38:23.196437",
   "default": null,
   "depends_on": null,
   "description": null,
   "docstatus": 0,
   "dt": "Dispatch Form",
   "fetch_from": null,
   "fetch_if_empty": 0,
   "fieldname": "custom_week_",
   "fieldtype": "Int",
   "hidden": 0,
   "hide_border": 0,
   "hide_days": 0,
   "hide_seconds": 0,
   "idx": 10,
   "ignore_user_permissions": 0,
   "ignore_xss_filter": 0,
   "in_global_search": 0,
   "in_list_view": 0,
   "in_preview": 0,
   "in_standard_filter": 0,
   "insert_after": "custom_arrival_time_at_dropoff_point",
   "is_system_generated": 0,
   "is_virtual": 0,
   "label": "Week No",
   "length": 0,
   "link_filters": null,
   "mandatory_depends_on": null,
   "modified": "2025-02-09 21:38:23.196437",
   "modified_by": "Administrator",
   "module": null,
   "name": "Dispatch Form-custom_week_",
   "no_copy": 0,
   "non_negative": 0,
   "options": null,
   "owner": "Administrator",
   "permlevel": 0,
   "placeholder": null,
   "precision": "",
   "print_hide": 0,
   "print_hide_if_no_value": 0,
   "print_width": null,
   "read_only": 1,
   "read_only_depends_on": null,
   "report_hide": 0,
   "reqd": 0,
   "search_index": 0,
   "show_dashboard": 0,
   "sort_options": 0,
   "translatable": 0,
   "unique": 0,
   "width": null
  }
 ],
 "custom_perms": [],
 "doctype": "Dispatch Form",
 "links": [],
 "property_setters": [
  {
   "_assign": null,
   "_comments": null,
   "_liked_by": null,
   "_user_tags": null,
   "creation": "2025-02-05 10:43:12.630386",
   "default_value": null,
   "doc_type": "Dispatch Form",
   "docstatus": 0,
   "doctype_or_field": "DocType",
   "field_name": null,
   "idx": 0,
   "is_system_generated": 1,
   "modified": "2025-02-26 20:35:25.718085",
   "modified_by": "Administrator",
   "module": null,
   "name": "Dispatch Form-main-default_print_format",
   "owner": "Administrator",
   "property": "default_print_format",
   "property_type": "Data",
   "row_name": null,
   "value": "Dispatch Form - Tambuzi"
  },
  {
   "_assign": null,
   "_comments": null,
   "_liked_by": null,
   "_user_tags": null,
   "creation": "2025-02-27 11:51:13.322951",
   "default_value": null,
   "doc_type": "Dispatch Form",
   "docstatus": 0,
   "doctype_or_field": "DocType",
   "field_name": null,
   "idx": 0,
   "is_system_generated": 0,
   "modified": "2025-02-27 11:51:13.322951",
   "modified_by": "Administrator",
   "module": null,
   "name": "Dispatch Form-main-field_order",
   "owner": "Administrator",
   "property": "field_order",
   "property_type": "Data",
   "row_name": null,
   "value": "[\"section_break_sxd5\", \"amended_from\", \"custom_company\", \"naming_series\", \"custom_date\", \"custom_column_break_pdozs\", \"custom_trip\", \"custom_sample_temps\", \"custom_arrival_time_at_dropoff_point\", \"custom_week_\", \"custom_section_break_fcmtc\", \"dispatch_form_item\", \"custom_sku_summary\", \"custom_section_break_mwy3p\", \"custom_total_number_of_boxes_dispatched\", \"custom_dispatch_time\", \"custom_column_break_y2q6x\", \"custom_truck_drivers_name\", \"truck_reg_no\", \"custom_section_break_63l1f\", \"custom_comments\", \"custom_shipment_confirmation_awb_signature\", \"custom_column_break_vppm6\", \"custom_compiled_bypacking_supervisor\", \"custom_signature\", \"custom_security_supervisor\"]"
  },
  {
   "_assign": null,
   "_comments": null,
   "_liked_by": null,
   "_user_tags": null,
   "creation": "2025-02-09 20:41:03.250921",
   "default_value": null,
   "doc_type": "Dispatch Form",
   "docstatus": 0,
   "doctype_or_field": "DocField",
   "field_name": "naming_series",
   "idx": 0,
   "is_system_generated": 0,
   "modified": "2025-02-26 20:35:25.738298",
   "modified_by": "Administrator",
   "module": null,
   "name": "Dispatch Form-naming_series-hidden",
   "owner": "Administrator",
   "property": "hidden",
   "property_type": "Check",
   "row_name": null,
   "value": "1"
  },
  {
   "_assign": null,
   "_comments": null,
   "_liked_by": null,
   "_user_tags": null,
   "creation": "2025-02-05 09:39:01.772426",
   "default_value": null,
   "doc_type": "Dispatch Form",
   "docstatus": 0,
   "doctype_or_field": "DocField",
   "field_name": "naming_series",
   "idx": 0,
   "is_system_generated": 0,
   "modified": "2025-02-26 20:35:25.750588",
   "modified_by": "Administrator",
   "module": null,
   "name": "Dispatch Form-naming_series-options",
   "owner": "Administrator",
   "property": "options",
   "property_type": "Text",
   "row_name": null,
   "value": "DF-.YYYY.-"
  }
 ],
 "sync_on_migrate": 1
}